recsys_pipeliner/__init__.py
recsys_pipeliner/_version.py
recsys_pipeliner/containers/sklearn/__init__.py
recsys_pipeliner/containers/sklearn/handler_service.py
recsys_pipeliner/containers/sklearn/handlers.py
recsys_pipeliner/containers/sklearn/mms.py
recsys_pipeliner/containers/sklearn/serving.py
recsys_pipeliner/containers/sklearn/training.py
recsys_pipeliner/recommendations/encoder.py
recsys_pipeliner/recommendations/recommender.py
recsys_pipeliner/recommendations/transformer.py
recsys_pipeliner/recommendations/utils.py
recsys_pipeliner-0.0.6.dist-info/licenses/LICENSE
recsys_pipeliner-0.0.6.dist-info/METADATA
recsys_pipeliner-0.0.6.dist-info/WHEEL
recsys_pipeliner-0.0.6.dist-info/entry_points.txt
recsys_pipeliner-0.0.6.dist-info/top_level.txt
recsys_pipeliner-0.0.6.dist-info/RECORD
