Metadata-Version: 2.4
Name: recsys-pipeliner
Version: 0.0.6
Requires-Python: >=3.11
License-File: LICENSE
Requires-Dist: boto3
Requires-Dist: multi-model-server>=1.1.11
Requires-Dist: numpy
Requires-Dist: pandas~=2.2.3
Requires-Dist: pydantic
Requires-Dist: sagemaker-inference>=1.10.1
Requires-Dist: sagemaker-training>=5.1.0
Requires-Dist: sagemaker~=2.245.0
Requires-Dist: scikit-learn~=1.6.1
Requires-Dist: scipy
Provides-Extra: jupyter
Requires-Dist: matplotlib; extra == "jupyter"
Requires-Dist: matspy; extra == "jupyter"
Requires-Dist: sagemaker[local]~=2.245.0; extra == "jupyter"
Requires-Dist: seaborn; extra == "jupyter"
Requires-Dist: ipykernel; extra == "jupyter"
Requires-Dist: python-dotenv; extra == "jupyter"
Provides-Extra: torch
Requires-Dist: torch; extra == "torch"
Dynamic: license-file
